{
    "advanced": {
        "ampFooterText": "",
        "ampGaId": "",
        "ampImage": "",
        "ampIsEnabled": 0,
        "ampPrimaryColor": "#039be5",
        "ampShare": 1,
        "ampShareFacebook": 1,
        "ampShareFacebookId": "",
        "ampShareLinkedIn": 1,
        "ampSharePinterest": 1,
        "ampShareSystem": 1,
        "ampShareTumblr": 1,
        "ampShareTwitter": 1,
        "ampShareWhatsapp": 1,
        "authorMetaDescription": "One of the two authors writing for twoandahalfvan.eu.",
        "authorMetaTitle": "%authorname - Author on %sitename",
        "authorNoIndexPagination": true,
        "authorNoPagination": true,
        "cssCompression": 1,
        "customBodyCode": "",
        "customFooterAmpCode": "",
        "customFooterCode": "",
        "customHeadAmpCode": "",
        "customHeadCode": "",
        "displayEmptyAuthors": false,
        "displayEmptyTags": false,
        "errorMetaDescription": "",
        "errorMetaTitle": "404 - Dead End?",
        "featuredPostsListingOrder": "ASC",
        "featuredPostsListingOrderBy": "created_at",
        "feed": {
            "enableJson": 1,
            "enableRss": 1,
            "numberOfPosts": 10,
            "showFeaturedImage": 1,
            "showFullText": 1,
            "title": "displayName",
            "titleValue": ""
        },
        "gdpr": {
            "articleExternalUrl": "",
            "articleId": 15,
            "articleLinkType": "internal",
            "badgeLabel": "Cookie Policy",
            "behaviour": "badge",
            "behaviourLink": "#cookie-settings",
            "enabled": true,
            "groups": [
                {
                    "id": "-",
                    "name": "Required"
                }
            ],
            "popupDesc": "Our website may set cookies for certain functionality.",
            "popupTitlePrimary": "This website may use cookies",
            "readMoreLinkLabel": "Privacy Policy",
            "saveButtonLabel": "OK"
        },
        "hiddenPostsListingOrder": "DESC",
        "hiddenPostsListingOrderBy": "created_at",
        "homepageNoIndexPagination": false,
        "htmlCompression": 1,
        "htmlCompressionRemoveComments": 1,
        "imagesQuality": 60,
        "metaDescription": "Blog about vanlife and travel across Europe. Find camper stories like \"How to build your van\" and travel blog posts. ",
        "metaRobotsAuthors": "noindex, follow",
        "metaRobotsError": "noindex, follow",
        "metaRobotsIndex": "index, follow",
        "metaRobotsSearch": "noindex, follow",
        "metaRobotsTags": "noindex, follow",
        "metaTitle": "%sitename - Vanlife in Europe",
        "noIndexThisPage": false,
        "openGraphAppId": "",
        "openGraphEnabled": 1,
        "openGraphImage": "",
        "postMetaDescription": "Blog post on twoandahalfvan.eu: Travelling in a van across Europe. ",
        "postMetaTitle": "%posttitle - %sitename",
        "postUseTextWithoutCustomExcerpt": false,
        "postsListingOrder": "DESC",
        "postsListingOrderBy": "created_at",
        "relatedPostsCriteria": "tags",
        "relatedPostsIncludeAllPosts": false,
        "relatedPostsOrder": "default",
        "searchMetaDescription": "",
        "searchMetaTitle": "Search",
        "sitemapAddAuthors": 1,
        "sitemapAddExternalImages": 0,
        "sitemapAddHomepage": 1,
        "sitemapAddTags": 1,
        "sitemapEnabled": 1,
        "sitemapExcludedFiles": "",
        "tagMetaDescription": "",
        "tagMetaTitle": "%tagname - %sitename",
        "tagNoIndexPagination": false,
        "tagNoPagination": false,
        "twitterCardsEnabled": 1,
        "twitterCardsType": "summary",
        "twitterUsername": "",
        "urls": {
            "addIndex": false,
            "authorsPrefix": "authors",
            "cleanUrls": true,
            "errorPage": "404.html",
            "pageName": "page",
            "searchPage": "search.html",
            "tagsPrefix": "tag"
        },
        "usePageTitleInsteadItemName": false,
        "versionSuffix": 1
    },
    "deployment": {
        "askforpassword": false,
        "github": {
            "branch": "master",
            "parallelOperations": 1,
            "repo": "twoandahalfvan.github.io",
            "server": "api.github.com",
            "token": "publii-gh-token twoandahalfvan",
            "user": "twoandahalfvan"
        },
        "gitlab": {
            "branch": "",
            "repo": "",
            "server": "https://gitlab.com/",
            "token": ""
        },
        "google": {
            "bucket": "",
            "key": "",
            "prefix": ""
        },
        "manual": {
            "output": "",
            "outputDirectory": ""
        },
        "netlify": {
            "id": "",
            "token": ""
        },
        "passphrase": "",
        "password": "",
        "path": "",
        "port": "",
        "protocol": "github-pages",
        "rejectUnauthorized": true,
        "relativeUrls": false,
        "s3": {
            "acl": "public-read",
            "bucket": "",
            "id": "",
            "key": "",
            "prefix": "",
            "region": "",
            "removeFiles": false
        },
        "server": "",
        "sftpkey": "",
        "username": ""
    },
    "displayName": "twoandahalfvan",
    "domain": "https://twoandahalfvan.eu",
    "language": "en",
    "logo": {
        "color": 1,
        "icon": "web-ice-cream"
    },
    "name": "twoandahalfvan",
    "syncDate": 1585220882053,
    "synced": "synced",
    "theme": "simple"
}